server.py
qinglong_mcp_cloud-0.1.2.dist-info/METADATA
qinglong_mcp_cloud-0.1.2.dist-info/WHEEL
qinglong_mcp_cloud-0.1.2.dist-info/entry_points.txt
qinglong_mcp_cloud-0.1.2.dist-info/licenses/LICENSE
qinglong_mcp_cloud-0.1.2.dist-info/RECORD
