Metadata-Version: 2.4
Name: qinglong-mcp-cloud
Version: 0.1.2
Summary: Stateless MCP server for Qinglong Panel - Cloud deployment version
Author-email: Pholex <pholex@gmail.com>
License: Apache-2.0
License-File: LICENSE
Keywords: automation,cloud,mcp,qinglong,stateless
Classifier: Development Status :: 3 - Alpha
Classifier: Intended Audience :: Developers
Classifier: Programming Language :: Python :: 3
Classifier: Programming Language :: Python :: 3.8
Classifier: Programming Language :: Python :: 3.9
Classifier: Programming Language :: Python :: 3.10
Classifier: Programming Language :: Python :: 3.11
Classifier: Programming Language :: Python :: 3.12
Requires-Python: >=3.8
Requires-Dist: requests
